{"errors":[],"warnings":[],"namedChunkGroups":{"polyfill":{"chunks":[0,5],"assets":["webpack-runtime-2414eb31a9300862ded4.js","webpack-runtime-2414eb31a9300862ded4.js.map","polyfill-392310f31b82912380e3.js","polyfill-392310f31b82912380e3.js.map"],"children":{},"childAssets":{}},"app":{"chunks":[0,6,4,2],"assets":["webpack-runtime-2414eb31a9300862ded4.js","webpack-runtime-2414eb31a9300862ded4.js.map","styles.e02cb94428ca05897279.css","styles-c4fa86dfd4ad05097eee.js","styles-c4fa86dfd4ad05097eee.js.map","framework-06f646d936b841f99ebd.js","framework-06f646d936b841f99ebd.js.map","app-d2e61d648c08f02fef60.js","app-d2e61d648c08f02fef60.js.map"],"children":{},"childAssets":{}},"component---src-pages-index-tsx":{"chunks":[1,3],"assets":["1bfc9850-1cb0f69d265c3bceb853.js","1bfc9850-1cb0f69d265c3bceb853.js.map","component---src-pages-index-tsx-6a612e6da2a63d1155da.js","component---src-pages-index-tsx-6a612e6da2a63d1155da.js.map"],"children":{},"childAssets":{}}},"assetsByChunkName":{"polyfill":["webpack-runtime-2414eb31a9300862ded4.js","polyfill-392310f31b82912380e3.js"],"app":["webpack-runtime-2414eb31a9300862ded4.js","styles.e02cb94428ca05897279.css","styles-c4fa86dfd4ad05097eee.js","framework-06f646d936b841f99ebd.js","app-d2e61d648c08f02fef60.js"],"component---src-pages-index-tsx":["1bfc9850-1cb0f69d265c3bceb853.js","component---src-pages-index-tsx-6a612e6da2a63d1155da.js"]}}